<?xml version="1.0" encoding="utf-8" standalone="no"?>
<!DOCTYPE dotfuscator SYSTEM "http://www.preemptive.com/dotfuscator/dtd/dotfuscator_v2.1.dtd">
<dotfuscator version="2.1">
  <!--This is application generated code. Do not edit manually.-->
  <global />
  <input>
    <asmlist>
      <inputassembly>
        <option>honoroas</option>
        <option>stripoa</option>
        <option>library</option>
        <file dir="E:\My Projects\Shop Management Solution\Shop Management V3\Shop Management\ShopManager\bin\x86\Debug" name="ShopManager.Controls.dll" />
      </inputassembly>
      <inputassembly>
        <option>honoroas</option>
        <option>stripoa</option>
        <option>library</option>
        <file dir="E:\My Projects\Shop Management Solution\Shop Management V3\Shop Management\ShopManager\bin\x86\Debug" name="ShopManager.exe" />
      </inputassembly>
      <inputassembly>
        <option>honoroas</option>
        <option>stripoa</option>
        <option>library</option>
        <file dir="E:\My Projects\Shop Management Solution\Shop Management V3\Shop Management\ShopManager\bin\x86\Debug" name="ShopManager.ProjectResources.dll" />
      </inputassembly>
    </asmlist>
  </input>
  <output>
    <file dir="${configdir}\Dotfuscated" />
  </output>
  <renaming>
    <mapping>
      <mapoutput overwrite="false">
        <file dir="${configdir}\Dotfuscated" name="Map.xml" />
      </mapoutput>
    </mapping>
  </renaming>
</dotfuscator>